LICENSE
MANIFEST.in
README.md
requirements.txt
setup.cfg
setup.py
musixmatch/__init__.py
musixmatch/album.py
musixmatch/api.py
musixmatch/artist.py
musixmatch/chart.py
musixmatch/client.py
musixmatch/expections.py
musixmatch/models.py
musixmatch/track.py
python_musixmatch.egg-info/PKG-INFO
python_musixmatch.egg-info/SOURCES.txt
python_musixmatch.egg-info/dependency_links.txt
python_musixmatch.egg-info/requires.txt
python_musixmatch.egg-info/top_level.txt
python_musixmatch.egg-info/zip-safe