Metadata-Version: 1.1
Name: python-musixmatch
Version: 1.0.0
Summary: A Python client for the Musixmatch API.
Home-page: http://github.com/yakupadakli/python-musixmatch.git
Author: Yakup Adaklı
Author-email: yakup.adakli@gmail.com
License: MIT
Keywords: Musixmatch library lyrics tracks artist album music
Platform: UNKNOWN
Classifier: Development Status :: 5 - Production/Stable
Classifier: Topic :: Software Development :: Libraries
Classifier: License :: OSI Approved :: MIT License
Classifier: Operating System :: OS Independent
Classifier: Programming Language :: Python :: 2.7
Classifier: Programming Language :: Python :: 3.4
Classifier: Programming Language :: Python :: 3.5
Classifier: Programming Language :: Python :: 3.6
